phylodata/__init__.py
phylodata/data_types.py
phylodata/errors.py
phylodata/main.py
phylodata/paper_with_experiment.py
phylodata/version.py
phylodata/loader/download_file.py
phylodata/loader/get_files.py
phylodata/loader/load_experiment.py
phylodata/loader/preview_env.py
phylodata/maintenance/create_new_version.py
phylodata/maintenance/manage_db.py
phylodata/maintenance/manage_files.py
phylodata/phylodata.egg-info/PKG-INFO
phylodata/phylodata.egg-info/SOURCES.txt
phylodata/phylodata.egg-info/dependency_links.txt
phylodata/phylodata.egg-info/entry_points.txt
phylodata/phylodata.egg-info/requires.txt
phylodata/phylodata.egg-info/top_level.txt
"phylodata/process/__init__,py"
phylodata/process/change_language.py
phylodata/process/change_ncbi.py
phylodata/process/module.py
phylodata/process/remove_classification.py
phylodata/process/ui.py
phylodata/process/evolutionary_model/__init__.py
phylodata/process/evolutionary_model/evolutionary_model_module.py
phylodata/process/evolutionary_model/models.json
phylodata/process/evolutionary_model/parse_beast2_packages.py
phylodata/process/evolutionary_model/parse_evolutionary_model.py
phylodata/process/experiment/__init__.py
phylodata/process/experiment/experiment_module.py
phylodata/process/experiment/human_readable_id.py
phylodata/process/files/__init__.py
phylodata/process/files/files_module.py
phylodata/process/files/parse_files.py
phylodata/process/paper/__init__.py
phylodata/process/paper/bibtex.py
phylodata/process/paper/doi.py
phylodata/process/paper/mail.py
phylodata/process/paper/paper_module.py
phylodata/process/samples/__init__.py
phylodata/process/samples/add_language_metadata.py
phylodata/process/samples/add_nucleotide_metadata.py
phylodata/process/samples/add_protein_metadata.py
phylodata/process/samples/language_utils.py
phylodata/process/samples/parse_beast2_samples.py
phylodata/process/samples/run_blast.py
phylodata/process/samples/sample_name_matching.py
phylodata/process/samples/samples_module.py
phylodata/process/samples/sequence_utils.py
phylodata/process/samples/taxon_classification.py
phylodata/process/trees/__init__.py
phylodata/process/trees/parse_trees.py
phylodata/process/trees/trees_module.py
phylodata/process/utils/__init__.py
phylodata-0.51.0.dist-info/METADATA
phylodata-0.51.0.dist-info/WHEEL
phylodata-0.51.0.dist-info/entry_points.txt
phylodata-0.51.0.dist-info/RECORD
