Metadata-Version: 2.4
Name: phylodata
Version: 0.51.0
Summary: This library allows you to access experiments on PhyloData using Python.
Requires-Python: >=3.10
Requires-Dist: bibtexparser>=2.0.0b1
Requires-Dist: biopython>=1.85
Requires-Dist: click>=8.2.1
Requires-Dist: commonnexus>=1.9.2
Requires-Dist: loguru>=0.7.3
Requires-Dist: msgspec>=0.19.0
Requires-Dist: nanoid>=2.0.0
Requires-Dist: nicegui>=2.20.0
Requires-Dist: pytest>=8.4.1
Requires-Dist: rapidfuzz>=3.13.0
Requires-Dist: rdflib>=7.1.4
Requires-Dist: streamlit>=1.46.0
Requires-Dist: taxoniq>=1.0.3
Requires-Dist: tqdm>=4.67.1
